meson_ui-0.20.1.data/data/share/man/man1/meson-ui.1
mesonui/__init__.py
mesonui/authorinfo.py
mesonui/commandline.py
mesonui/mesonuiinit.py
mesonui/mesonuilogs.py
mesonui/mesonuimain.py
mesonui/mesonuitheme.py
mesonui/packageinfo.py
mesonui/projectinfo.py
mesonui/containers/__init__.py
mesonui/containers/doublylist.py
mesonui/containers/queue.py
mesonui/containers/stack.py
mesonui/dashboard/__init__.py
mesonui/dashboard/appdashboard.py
mesonui/dashboard/buildoptions.py
mesonui/dashboard/projectinfo.py
mesonui/dashboard/tests.py
mesonui/mesonuilib/__init__.py
mesonui/mesonuilib/backend.py
mesonui/mesonuilib/buildsystem.py
mesonui/mesonuilib/coredata.py
mesonui/mesonuilib/mapmeson.py
mesonui/mesonuilib/outputconsole.py
mesonui/mesonuilib/utilitylib.py
mesonui/mesonuilib/xmlbuilder.py
mesonui/mesonuilib/appconfig/__init__.py
mesonui/mesonuilib/appconfig/backend.py
mesonui/mesonuilib/appconfig/base.py
mesonui/mesonuilib/appconfig/core.py
mesonui/mesonuilib/appconfig/dist.py
mesonui/mesonuilib/appconfig/init.py
mesonui/mesonuilib/appconfig/install.py
mesonui/mesonuilib/appconfig/path.py
mesonui/mesonuilib/appconfig/test.py
mesonui/mesonuilib/backends/__init__.py
mesonui/mesonuilib/backends/backendimpl.py
mesonui/mesonuilib/backends/codeblocks.py
mesonui/mesonuilib/backends/gnome.py
mesonui/mesonuilib/backends/kdevelop.py
mesonui/mesonuilib/backends/qtcreator.py
mesonui/mesonuilib/mesonapi/__init__.py
mesonui/mesonuilib/mesonapi/buildoptions.py
mesonui/mesonuilib/mesonapi/projectinfo.py
mesonui/mesonuilib/mesonbuild/__init__.py
mesonui/mesonuilib/mesonbuild/clean.py
mesonui/mesonuilib/mesonbuild/compile.py
mesonui/mesonuilib/mesonbuild/configure.py
mesonui/mesonuilib/mesonbuild/dist.py
mesonui/mesonuilib/mesonbuild/init.py
mesonui/mesonuilib/mesonbuild/install.py
mesonui/mesonuilib/mesonbuild/setup.py
mesonui/mesonuilib/mesonbuild/subprojects.py
mesonui/mesonuilib/mesonbuild/test.py
mesonui/mesonuilib/mesonbuild/version.py
mesonui/mesonuilib/mesonbuild/wrap.py
meson_ui-0.20.1.dist-info/LICENSE
meson_ui-0.20.1.dist-info/METADATA
meson_ui-0.20.1.dist-info/WHEEL
meson_ui-0.20.1.dist-info/entry_points.txt
meson_ui-0.20.1.dist-info/top_level.txt
meson_ui-0.20.1.dist-info/zip-safe
meson_ui-0.20.1.dist-info/RECORD
