Metadata-Version: 2.1
Name: meson-ui
Version: 0.20.1
Summary: Meson-UI is an open source build GUI meant to be both extremely fast,
Requires-Dist: meson
Requires-Dist: ninja
Requires-Dist: PyQt5
